librarian/.env.example
librarian/__init__.py
librarian/cli.py
librarian/config.py
librarian/indexing.py
librarian/server.py
librarian/types.py
librarian/processing/__init__.py
librarian/processing/manager.py
librarian/processing/embed/__init__.py
librarian/processing/embed/base.py
librarian/processing/embed/local.py
librarian/processing/embed/openai.py
librarian/processing/parsers/__init__.py
librarian/processing/parsers/base.py
librarian/processing/parsers/code.py
librarian/processing/parsers/image.py
librarian/processing/parsers/md.py
librarian/processing/parsers/obsidian.py
librarian/processing/parsers/pdf.py
librarian/processing/parsers/registry.py
librarian/processing/transform/__init__.py
librarian/processing/transform/chunker.py
librarian/processing/transform/code.py
librarian/processing/transform/pdf.py
librarian/providers/__init__.py
librarian/providers/anthropic.py
librarian/providers/base.py
librarian/providers/oai.py
librarian/retrieval/__init__.py
librarian/retrieval/search.py
librarian/sources/__init__.py
librarian/sources/codebase.py
librarian/sources/ignore.py
librarian/storage/__init__.py
librarian/storage/database.py
librarian/storage/fts_store.py
librarian/storage/migrations.py
librarian/storage/vector_store.py
librarian/utils/__init__.py
librarian/utils/timeframe.py
agent_library-0.8.0.dist-info/METADATA
agent_library-0.8.0.dist-info/WHEEL
agent_library-0.8.0.dist-info/entry_points.txt
agent_library-0.8.0.dist-info/RECORD
