Metadata-Version: 2.4
Name: agent-library
Version: 0.8.0
Summary: Multi-modal knowledge library with vector and full-text search for text, code, images, and PDFs
Author-email: "Arcade.dev" <dev@arcade.dev>
License-Expression: MIT
Keywords: ai,code,embeddings,knowledge-management,markdown,mcp,multimodal,search,vector
Classifier: Development Status :: 4 - Beta
Classifier: Environment :: Console
Classifier: Intended Audience :: Developers
Classifier: License :: OSI Approved :: MIT License
Classifier: Operating System :: OS Independent
Classifier: Programming Language :: Python :: 3
Classifier: Programming Language :: Python :: 3.10
Classifier: Programming Language :: Python :: 3.11
Classifier: Programming Language :: Python :: 3.12
Classifier: Topic :: Software Development :: Libraries :: Python Modules
Classifier: Topic :: Text Processing :: Indexing
Requires-Python: >=3.10
Requires-Dist: arcade-mcp-server>=0.1.0
Requires-Dist: numpy>=1.24.0
Requires-Dist: python-frontmatter>=1.0.0
Requires-Dist: pyyaml>=6.0
Requires-Dist: rich>=13.0.0
Requires-Dist: sentence-transformers>=2.2.0
Requires-Dist: sqlite-vec>=0.1.0
Requires-Dist: typer[all]>=0.9.0
Provides-Extra: all
Requires-Dist: pillow>=10.0.0; extra == 'all'
Requires-Dist: pypdf>=4.0.0; extra == 'all'
Requires-Dist: pytesseract>=0.3.10; extra == 'all'
Requires-Dist: torch>=2.0.0; extra == 'all'
Requires-Dist: torchvision>=0.15.0; extra == 'all'
Requires-Dist: transformers>=4.30.0; extra == 'all'
Requires-Dist: tree-sitter-javascript>=0.21.0; extra == 'all'
Requires-Dist: tree-sitter-python>=0.21.0; extra == 'all'
Requires-Dist: tree-sitter>=0.21.0; extra == 'all'
Provides-Extra: code
Requires-Dist: torch>=2.0.0; extra == 'code'
Requires-Dist: transformers>=4.30.0; extra == 'code'
Requires-Dist: tree-sitter-javascript>=0.21.0; extra == 'code'
Requires-Dist: tree-sitter-python>=0.21.0; extra == 'code'
Requires-Dist: tree-sitter>=0.21.0; extra == 'code'
Provides-Extra: dev
Requires-Dist: mypy>=1.5.1; extra == 'dev'
Requires-Dist: pre-commit>=3.4.0; extra == 'dev'
Requires-Dist: pytest-asyncio>=0.25.0; extra == 'dev'
Requires-Dist: pytest-cov>=4.0.0; extra == 'dev'
Requires-Dist: pytest>=8.3.0; extra == 'dev'
Requires-Dist: ruff>=0.7.4; extra == 'dev'
Requires-Dist: types-pyyaml>=6.0.1; extra == 'dev'
Provides-Extra: evals
Requires-Dist: arcade-mcp[evals]>=1.0.0; extra == 'evals'
Provides-Extra: ocr
Requires-Dist: pillow>=10.0.0; extra == 'ocr'
Requires-Dist: pytesseract>=0.3.10; extra == 'ocr'
Provides-Extra: pdf
Requires-Dist: pypdf>=4.0.0; extra == 'pdf'
Provides-Extra: vision
Requires-Dist: pillow>=10.0.0; extra == 'vision'
Requires-Dist: torch>=2.0.0; extra == 'vision'
Requires-Dist: torchvision>=0.15.0; extra == 'vision'
Requires-Dist: transformers>=4.30.0; extra == 'vision'
